booklib/__init__.py
booklib-0.0.0.dist-info/METADATA
booklib-0.0.0.dist-info/WHEEL
booklib-0.0.0.dist-info/top_level.txt
booklib-0.0.0.dist-info/RECORD
