Metadata-Version: 2.4
Name: booklib
Version: 0.0.0
Summary: Coming soon
